clout/__init__.py
clout/_loaders/__init__.py
clout/_loaders/cli.py
clout/_loaders/env.py
clout/_loaders/multi.py
clout/_loaders/parsing.py
clout/_util.py
clout/exceptions.py
clout-0.1.14.dist-info/LICENSE
clout-0.1.14.dist-info/WHEEL
clout-0.1.14.dist-info/METADATA
clout-0.1.14.dist-info/RECORD
