Metadata-Version: 2.1
Name: clout
Version: 0.1.14
Summary: Command-line Object Utility Tool
Author: Clout contributors
Author-email: python-clout@users.noreply.github.com
Requires-Python: >=3.7,<4.0
Classifier: Intended Audience :: Developers
Classifier: Programming Language :: Python :: 3
Classifier: Programming Language :: Python :: 3.6
Classifier: Programming Language :: Python :: 3.7
Classifier: Programming Language :: Python :: 3.8
Classifier: Programming Language :: Python :: Implementation :: CPython
Classifier: Programming Language :: Python :: Implementation :: PyPy
Provides-Extra: docs
Requires-Dist: appdirs (>=1.4,<2.0)
Requires-Dist: attrs (>=19.2.0)
Requires-Dist: click
Requires-Dist: dataclasses (>=0.6.0,<0.7.0)
Requires-Dist: desert (>=2019.11.06)
Requires-Dist: glom (>=19.2,<20.0)
Requires-Dist: importlib_resources (>=1.0,<2.0)
Requires-Dist: inflection (>=0.3.1,<0.4.0)
Requires-Dist: lark-parser (>=0.7.3,<0.8.0)
Requires-Dist: marshmallow (>=3.0,<4.0)
Requires-Dist: typing-extensions (>=3.7,<4.0)
Requires-Dist: typing-inspect (>=0.4.0,<0.5.0)
